Metadata-Version: 2.1
Name: math-gb-distributions
Version: 1.3
Summary: Gaussian and Binomial distributions
Author: Javad Farshchi
Author-email: mjavad.farshchi@gmail.com
